lielab/__init__.py
lielab/cppLielab.cpython-313-x86_64-linux-gnu.so
lielab/domain/__init__.py
lielab/functions/__init__.py
lielab/functions/derivative.py
lielab/integrate/ODESolution.py
lielab/integrate/__init__.py
lielab/integrate/solve_ivp.py
lielab/integrate/IVPMethods/Coefficients.py
lielab/integrate/IVPMethods/IVPSettings.py
lielab/integrate/IVPMethods/RungeKutta.py
lielab/integrate/IVPMethods/__init__.py
lielab/testing/__init__.py
lielab/testing/test_main.py
lielab/utils/__init__.py
lielab/utils/utils.py
lielab-0.5.1.dist-info/LICENSE
lielab-0.5.1.dist-info/METADATA
lielab-0.5.1.dist-info/WHEEL
lielab-0.5.1.dist-info/RECORD
