Metadata-Version: 2.4
Name: lielab
Version: 0.5.1
Summary: Software for the geometric modeling and numerical analysis of systems, especially those in relation to Lie theory.
Author-Email: "Michael J. Sparapany" <mjspara@sandia.gov>
License-Expression: MIT
Project-URL: Homepage, https://github.com/sandialabs/Lielab
Requires-Python: >=3.8
Requires-Dist: numpy
Provides-Extra: test
Requires-Dist: pytest; extra == "test"
Requires-Dist: scipy; extra == "test"
